{"labels": [{"name": "Occupied", "x1": 962, "y1": 294, "x2": 1245, "y2": 433}, {"name": "Occupied", "x1": 3, "y1": 567, "x2": 283, "y2": 704}, {"name": "Occupied", "x1": 4, "y1": 159, "x2": 283, "y2": 295}, {"name": "Occupied", "x1": 4, "y1": 24, "x2": 283, "y2": 160}, {"name": "Occupied", "x1": 962, "y1": 567, "x2": 1246, "y2": 705}, {"name": "Occupied", "x1": 3, "y1": 432, "x2": 283, "y2": 568}, {"name": "Occupied", "x1": 962, "y1": 160, "x2": 1244, "y2": 295}, {"name": "Occupied", "x1": 661, "y1": 23, "x2": 951, "y2": 160}, {"name": "Occupied", "x1": 4, "y1": 295, "x2": 283, "y2": 433}, {"name": "Occupied", "x1": 962, "y1": 432, "x2": 1245, "y2": 568}, {"name": "Occupied", "x1": 963, "y1": 23, "x2": 1244, "y2": 160}, {"name": "Vacant", "x1": 661, "y1": 160, "x2": 951, "y2": 295}, {"name": "Occupied", "x1": 661, "y1": 295, "x2": 951, "y2": 432}, {"name": "Occupied", "x1": 661, "y1": 433, "x2": 951, "y2": 567}, {"name": "Occupied", "x1": 661, "y1": 567, "x2": 952, "y2": 704}]}